piano_transcription_inference/__init__.py
piano_transcription_inference/config.py
piano_transcription_inference/inference.py
piano_transcription_inference/models.py
piano_transcription_inference/piano_vad.py
piano_transcription_inference/pytorch_utils.py
piano_transcription_inference/utilities.py
piano_transcription_inference-0.0.5.dist-info/METADATA
piano_transcription_inference-0.0.5.dist-info/WHEEL
piano_transcription_inference-0.0.5.dist-info/top_level.txt
piano_transcription_inference-0.0.5.dist-info/RECORD
