Metadata-Version: 2.1
Name: piano-transcription-inference
Version: 0.0.5
Summary: Piano transcription inference toolbox
Home-page: UNKNOWN
Author: Qiuqiang Kong
Author-email: qiuqiangkong@gmail.com
License: UNKNOWN
Platform: UNKNOWN
Classifier: Programming Language :: Python :: 3
Classifier: License :: OSI Approved :: MIT License
Classifier: Operating System :: OS Independent
Requires-Python: >=3.6
Requires-Dist: matplotlib
Requires-Dist: mido
Requires-Dist: librosa
Requires-Dist: torchlibrosa
